chromaterm/__init__.py
chromaterm/__main__.py
chromaterm/default_config.py
chromaterm/pcre.py
chromaterm/platform/__init__.py
chromaterm/platform/unix.py
chromaterm/platform/tests/__init__.py
chromaterm/platform/tests/test_unix.py
chromaterm/tests/__init__.py
chromaterm/tests/conftest.py
chromaterm/tests/test___init__.py
chromaterm/tests/test__main__.py
chromaterm/tests/test_default_config.py
chromaterm/tests/test_pcre.py
chromaterm-0.10.7.dist-info/LICENSE
chromaterm-0.10.7.dist-info/METADATA
chromaterm-0.10.7.dist-info/WHEEL
chromaterm-0.10.7.dist-info/entry_points.txt
chromaterm-0.10.7.dist-info/top_level.txt
chromaterm-0.10.7.dist-info/RECORD
