Metadata-Version: 2.1
Name: chromaterm
Version: 0.10.7
Summary: Color your Terminal with Regex!
Home-page: https://github.com/hSaria/ChromaTerm
Author: hSaria
Author-email: sariahajjar@gmail.com
License: MIT
Platform: UNKNOWN
Classifier: Intended Audience :: Information Technology
Classifier: Intended Audience :: System Administrators
Classifier: Intended Audience :: Telecommunications Industry
Classifier: License :: OSI Approved :: MIT License
Classifier: Programming Language :: Python :: 3
Classifier: Topic :: Terminals
Classifier: Topic :: Utilities
Requires-Python: >=3.6.0
License-File: LICENSE
Requires-Dist: psutil
Requires-Dist: PyYAML (>=5.1)
